odoo10_addon_project_description-10.0.1.0.0-py2.7-nspkg.pth
odoo/addons/project_description/__manifest__.py
odoo/addons/project_description/__init__.py
odoo/addons/project_description/README.rst
odoo/addons/project_description/models/project.py
odoo/addons/project_description/models/__init__.py
odoo/addons/project_description/i18n/zh_CN.po
odoo/addons/project_description/i18n/pt.po
odoo/addons/project_description/i18n/es.po
odoo/addons/project_description/i18n/hr.po
odoo/addons/project_description/i18n/sl.po
odoo/addons/project_description/i18n/pt_PT.po
odoo/addons/project_description/i18n/de.po
odoo/addons/project_description/i18n/fr.po
odoo/addons/project_description/i18n/pt_BR.po
odoo/addons/project_description/i18n/fi.po
odoo/addons/project_description/views/project_view.xml
odoo/addons/project_description/static/description/icon.png
odoo10_addon_project_description-10.0.1.0.0.dist-info/top_level.txt
odoo10_addon_project_description-10.0.1.0.0.dist-info/WHEEL
odoo10_addon_project_description-10.0.1.0.0.dist-info/RECORD
odoo10_addon_project_description-10.0.1.0.0.dist-info/metadata.json
odoo10_addon_project_description-10.0.1.0.0.dist-info/DESCRIPTION.rst
odoo10_addon_project_description-10.0.1.0.0.dist-info/METADATA
odoo10_addon_project_description-10.0.1.0.0.dist-info/namespace_packages.txt
